Workbook

Sheet Customers
A1: Customer_ID | B1: Customer_Name | C1: Region | D1: Segment | E1: Gender | F1: Age
A2: CUST001 | B2: John Walker | C2: North | D2: Home Office | E2: Male | F2: 34
A3: CUST002 | B3: Steven Moore | C3: South | D3: Consumer | E3: Female | F3: 26
A4: CUST003 | B4: Nancy Wright | C4: North | D4: Home Office | E4: Male | F4: 50
A5: CUST004 | B5: John Ramirez | C5: North | D5: Corporate | E5: Male | F5: 37
A6: CUST005 | B6: William Brown | C6: East | D6: Consumer | E6: Male | F6: 30
A7: CUST006 | B7: Anthony Flores | C7: South | D7: Home Office | E7: Female | F7: 45
A8: CUST007 | B8: Andrew Walker | C8: West | D8: Consumer | E8: Male | F8: 46
A9: CUST008 | B9: Emily Young | C9: South | D9: Consumer | E9: Male | F9: 30
A10: CUST009 | B10: Margaret Garcia | C10: East | D10: Consumer | E10: Male | F10: 63
A11: CUST010 | B11: Dorothy Jackson | C11: South | D11: Corporate | E11: Female | F11: 52
A12: CUST011 | B12: Margaret Anderson | C12: East | D12: Consumer | E12: Male | F12: 23
A13: CUST012 | B13: Elizabeth Nguyen | C13: East | D13: Consumer | E13: Male | F13: 35
... A1001: CUST1000 | B1001: Joseph Lopez | C1001: East | D1001: Consumer | E1001: Male | F1001: 47

Sheet Orders
A1: Order_ID | B1: Order_Date | C1: Customer_ID | D1: Product_Category | E1: Quantity | F1: Price_per_Unit | G1: Sales | H1: Discount | I1: Profit | J1: Month | K1: Profit_Margin | L1: Customer_Name | M1: Region | N1: Segment
A2: 1 | B2: 2023-11-24 | C2: CUST001 | D2: Beauty | E2: 3 | F2: 50 | G2: 150 | H2: 0.15 | I2: 20.82 | J2: =MONTH(B2) -> 11 | K2: =IF(G2=0,0,I2/G2) -> 0.1388 | L2: =VLOOKUP(C2,Customers!$A$2:$F$1001,2,FALSE()) -> John Walker | M2: =VLOOKUP(C2,Customers!$A$2:$F$1001,3,FALSE()) -> North | N2: =VLOOKUP(C2,Customers!$A$2:$F$1001,4,FALSE()) -> Home Office
A3: 2 | B3: 2023-02-27 | C3: CUST002 | D3: Clothing | E3: 2 | F3: 500 | G3: 1000 | H3: 0.1 | I3: 85.1 | J3: =MONTH(B3) -> 2 | K3: =IF(G3=0,0,I3/G3) -> 0.0851 | L3: =VLOOKUP(C3,Customers!$A$2:$F$1001,2,FALSE()) -> Steven Moore | M3: =VLOOKUP(C3,Customers!$A$2:$F$1001,3,FALSE()) -> South | N3: =VLOOKUP(C3,Customers!$A$2:$F$1001,4,FALSE()) -> Consumer
A4: 3 | B4: 2023-01-13 | C4: CUST003 | D4: Electronics | E4: 1 | F4: 30 | G4: 30 | H4: 0 | I4: 5.72 | J4: =MONTH(B4) -> 1 | K4: =IF(G4=0,0,I4/G4) -> 0.19066667 | L4: =VLOOKUP(C4,Customers!$A$2:$F$1001,2,FALSE()) -> Nancy Wright | M4: =VLOOKUP(C4,Customers!$A$2:$F$1001,3,FALSE()) -> North | N4: =VLOOKUP(C4,Customers!$A$2:$F$1001,4,FALSE()) -> Home Office
A5: 4 | B5: 2023-05-21 | C5: CUST004 | D5: Clothing | E5: 1 | F5: 500 | G5: 500 | H5: 0.1 | I5: 101.34 | J5: =MONTH(B5) -> 5 | K5: =IF(G5=0,0,I5/G5) -> 0.20268 | L5: =VLOOKUP(C5,Customers!$A$2:$F$1001,2,FALSE()) -> John Ramirez | M5: =VLOOKUP(C5,Customers!$A$2:$F$1001,3,FALSE()) -> North | N5: =VLOOKUP(C5,Customers!$A$2:$F$1001,4,FALSE()) -> Corporate
A6: 5 | B6: 2023-05-06 | C6: CUST005 | D6: Beauty | E6: 2 | F6: 50 | G6: 100 | H6: 0 | I6: 33.57 | J6: =MONTH(B6) -> 5 | K6: =IF(G6=0,0,I6/G6) -> 0.3357 | L6: =VLOOKUP(C6,Customers!$A$2:$F$1001,2,FALSE()) -> William Brown | M6: =VLOOKUP(C6,Customers!$A$2:$F$1001,3,FALSE()) -> East | N6: =VLOOKUP(C6,Customers!$A$2:$F$1001,4,FALSE()) -> Consumer
A7: 6 | B7: 2023-04-25 | C7: CUST006 | D7: Beauty | E7: 1 | F7: 30 | G7: 30 | H7: 0.15 | I7: 3.91 | J7: =MONTH(B7) -> 4 | K7: =IF(G7=0,0,I7/G7) -> 0.13033333 | L7: =VLOOKUP(C7,Customers!$A$2:$F$1001,2,FALSE()) -> Anthony Flores | M7: =VLOOKUP(C7,Customers!$A$2:$F$1001,3,FALSE()) -> South | N7: =VLOOKUP(C7,Customers!$A$2:$F$1001,4,FALSE()) -> Home Office
A8: 7 | B8: 2023-03-13 | C8: CUST007 | D8: Clothing | E8: 2 | F8: 25 | G8: 50 | H8: 0.1 | I8: 3.14 | J8: =MONTH(B8) -> 3 | K8: =IF(G8=0,0,I8/G8) -> 0.0628 | L8: =VLOOKUP(C8,Customers!$A$2:$F$1001,2,FALSE()) -> Andrew Walker | M8: =VLOOKUP(C8,Customers!$A$2:$F$1001,3,FALSE()) -> West | N8: =VLOOKUP(C8,Customers!$A$2:$F$1001,4,FALSE()) -> Consumer
A9: 8 | B9: 2023-02-22 | C9: CUST008 | D9: Electronics | E9: 4 | F9: 25 | G9: 100 | H9: 0 | I9: 14.27 | J9: =MONTH(B9) -> 2 | K9: =IF(G9=0,0,I9/G9) -> 0.1427 | L9: =VLOOKUP(C9,Customers!$A$2:$F$1001,2,FALSE()) -> Emily Young | M9: =VLOOKUP(C9,Customers!$A$2:$F$1001,3,FALSE()) -> South | N9: =VLOOKUP(C9,Customers!$A$2:$F$1001,4,FALSE()) -> Consumer
A10: 9 | B10: 2023-12-13 | C10: CUST009 | D10: Electronics | E10: 2 | F10: 300 | G10: 600 | H10: 0 | I10: 84.31 | J10: =MONTH(B10) -> 12 | K10: =IF(G10=0,0,I10/G10) -> 0.14051667 | L10: =VLOOKUP(C10,Customers!$A$2:$F$1001,2,FALSE()) -> Margaret Garcia | M10: =VLOOKUP(C10,Customers!$A$2:$F$1001,3,FALSE()) -> East | N10: =VLOOKUP(C10,Customers!$A$2:$F$1001,4,FALSE()) -> Consumer
A11: 10 | B11: 2023-10-07 | C11: CUST010 | D11: Clothing | E11: 4 | F11: 50 | G11: 200 | H11: 0.15 | I11: 10.09 | J11: =MONTH(B11) -> 10 | K11: =IF(G11=0,0,I11/G11) -> 0.05045 | L11: =VLOOKUP(C11,Customers!$A$2:$F$1001,2,FALSE()) -> Dorothy Jackson | M11: =VLOOKUP(C11,Customers!$A$2:$F$1001,3,FALSE()) -> South | N11: =VLOOKUP(C11,Customers!$A$2:$F$1001,4,FALSE()) -> Corporate
A12: 11 | B12: 2023-02-14 | C12: CUST011 | D12: Clothing | E12: 2 | F12: 50 | G12: 100 | H12: 0 | I12: 25.66 | J12: =MONTH(B12) -> 2 | K12: =IF(G12=0,0,I12/G12) -> 0.2566 | L12: =VLOOKUP(C12,Customers!$A$2:$F$1001,2,FALSE()) -> Margaret Anderson | M12: =VLOOKUP(C12,Customers!$A$2:$F$1001,3,FALSE()) -> East | N12: =VLOOKUP(C12,Customers!$A$2:$F$1001,4,FALSE()) -> Consumer
A13: 12 | B13: 2023-10-30 | C13: CUST012 | D13: Beauty | E13: 3 | F13: 25 | G13: 75 | H13: 0.2 | I13: 9.14 | J13: =MONTH(B13) -> 10 | K13: =IF(G13=0,0,I13/G13) -> 0.12186667 | L13: =VLOOKUP(C13,Customers!$A$2:$F$1001,2,FALSE()) -> Elizabeth Nguyen | M13: =VLOOKUP(C13,Customers!$A$2:$F$1001,3,FALSE()) -> East | N13: =VLOOKUP(C13,Customers!$A$2:$F$1001,4,FALSE()) -> Consumer
... A1001: 1000 | B1001: 2023-04-12 | C1001: CUST1000 | D1001: Electronics | E1001: 4 | F1001: 30 | G1001: 120 | H1001: 0 | I1001: 14.54 | J1001: =MONTH(B1001) -> 4 | K1001: =IF(G1001=0,0,I1001/G1001) -> 0.12116667 | L1001: =VLOOKUP(C1001,Customers!$A$2:$F$1001,2,FALSE()) -> Joseph Lopez | M1001: =VLOOKUP(C1001,Customers!$A$2:$F$1001,3,FALSE()) -> East | N1001: =VLOOKUP(C1001,Customers!$A$2:$F$1001,4,FALSE()) -> Consumer

Sheet KPI_Summary
A1: Task 2 - Business KPI Dashboard Summary
A2: KPI | B2: Value
A3: Total Sales | B3: =SUM(Orders!G2:G1001) -> 456000
A4: Total Profit | B4: =SUM(Orders!I2:I1001) -> 71306.28
A5: Overall Profit Margin | B5: =B4/B3 -> 0.15637342
A6: Total Orders | B6: =COUNTA(Orders!A2:A1001) -> 1000
A7: Total Customers | B7: =COUNTA(Customers!A2:A1001) -> 1000
A8: Average Order Value (AOV) | B8: =B3/B6 -> 456

Sheet Region_Analysis
A1: Sales & Profit by Region
A2: Region | B2: Total_Sales | C2: Total_Profit | D2: Profit_Margin | E2: Order_Count
A3: East | B3: =SUMIFS(Orders!$G$2:$G$1001,Orders!$M$2:$M$1001,A3) -> 99285 | C3: =SUMIFS(Orders!$I$2:$I$1001,Orders!$M$2:$M$1001,A3) -> 15799.24 | D3: =IF(B3=0,0,C3/B3) -> 0.15913018 | E3: =COUNTIFS(Orders!$M$2:$M$1001,A3) -> 246
A4: North | B4: =SUMIFS(Orders!$G$2:$G$1001,Orders!$M$2:$M$1001,A4) -> 133380 | C4: =SUMIFS(Orders!$I$2:$I$1001,Orders!$M$2:$M$1001,A4) -> 21697.21 | D4: =IF(B4=0,0,C4/B4) -> 0.16267214 | E4: =COUNTIFS(Orders!$M$2:$M$1001,A4) -> 278
A5: South | B5: =SUMIFS(Orders!$G$2:$G$1001,Orders!$M$2:$M$1001,A5) -> 110260 | C5: =SUMIFS(Orders!$I$2:$I$1001,Orders!$M$2:$M$1001,A5) -> 16793.99 | D5: =IF(B5=0,0,C5/B5) -> 0.15231262 | E5: =COUNTIFS(Orders!$M$2:$M$1001,A5) -> 242
A6: West | B6: =SUMIFS(Orders!$G$2:$G$1001,Orders!$M$2:$M$1001,A6) -> 113075 | C6: =SUMIFS(Orders!$I$2:$I$1001,Orders!$M$2:$M$1001,A6) -> 17015.84 | D6: =IF(B6=0,0,C6/B6) -> 0.15048278 | E6: =COUNTIFS(Orders!$M$2:$M$1001,A6) -> 234

Sheet Category_Analysis
A1: Sales & Profit Margin by Product Category
A2: Product_Category | B2: Total_Sales | C2: Total_Profit | D2: Profit_Margin | E2: Order_Count
A3: Beauty | B3: =SUMIFS(Orders!$G$2:$G$1001,Orders!$D$2:$D$1001,A3) -> 143515 | C3: =SUMIFS(Orders!$I$2:$I$1001,Orders!$D$2:$D$1001,A3) -> 36173.67 | D3: =IF(B3=0,0,C3/B3) -> 0.25205498 | E3: =COUNTIFS(Orders!$D$2:$D$1001,A3) -> 307
A4: Clothing | B4: =SUMIFS(Orders!$G$2:$G$1001,Orders!$D$2:$D$1001,A4) -> 155580 | C4: =SUMIFS(Orders!$I$2:$I$1001,Orders!$D$2:$D$1001,A4) -> 23804.99 | D4: =IF(B4=0,0,C4/B4) -> 0.15300803 | E4: =COUNTIFS(Orders!$D$2:$D$1001,A4) -> 351
A5: Electronics | B5: =SUMIFS(Orders!$G$2:$G$1001,Orders!$D$2:$D$1001,A5) -> 156905 | C5: =SUMIFS(Orders!$I$2:$I$1001,Orders!$D$2:$D$1001,A5) -> 11327.62 | D5: =IF(B5=0,0,C5/B5) -> 0.07219413 | E5: =COUNTIFS(Orders!$D$2:$D$1001,A5) -> 342

Sheet Region_x_Category
A1: Sales by Region and Category
A2: Region | B2: Beauty | C2: Clothing | D2: Electronics
A3: East | B3: =SUMIFS(Orders!$G$2:$G$1001,Orders!$M$2:$M$1001,$A3,Orders!$D$2:$D$1001,B$2) -> 33665 | C3: =SUMIFS(Orders!$G$2:$G$1001,Orders!$M$2:$M$1001,$A3,Orders!$D$2:$D$1001,C$2) -> 30820 | D3: =SUMIFS(Orders!$G$2:$G$1001,Orders!$M$2:$M$1001,$A3,Orders!$D$2:$D$1001,D$2) -> 34800
A4: North | B4: =SUMIFS(Orders!$G$2:$G$1001,Orders!$M$2:$M$1001,$A4,Orders!$D$2:$D$1001,B$2) -> 46500 | C4: =SUMIFS(Orders!$G$2:$G$1001,Orders!$M$2:$M$1001,$A4,Orders!$D$2:$D$1001,C$2) -> 46680 | D4: =SUMIFS(Orders!$G$2:$G$1001,Orders!$M$2:$M$1001,$A4,Orders!$D$2:$D$1001,D$2) -> 40200
A5: South | B5: =SUMIFS(Orders!$G$2:$G$1001,Orders!$M$2:$M$1001,$A5,Orders!$D$2:$D$1001,B$2) -> 36815 | C5: =SUMIFS(Orders!$G$2:$G$1001,Orders!$M$2:$M$1001,$A5,Orders!$D$2:$D$1001,C$2) -> 31815 | D5: =SUMIFS(Orders!$G$2:$G$1001,Orders!$M$2:$M$1001,$A5,Orders!$D$2:$D$1001,D$2) -> 41630
A6: West | B6: =SUMIFS(Orders!$G$2:$G$1001,Orders!$M$2:$M$1001,$A6,Orders!$D$2:$D$1001,B$2) -> 26535 | C6: =SUMIFS(Orders!$G$2:$G$1001,Orders!$M$2:$M$1001,$A6,Orders!$D$2:$D$1001,C$2) -> 46265 | D6: =SUMIFS(Orders!$G$2:$G$1001,Orders!$M$2:$M$1001,$A6,Orders!$D$2:$D$1001,D$2) -> 40275

Sheet Segment_Analysis
A1: Sales & Profit by Customer Segment
A2: Segment | B2: Total_Sales | C2: Total_Profit | D2: Profit_Margin | E2: Order_Count
A3: Consumer | B3: =SUMIFS(Orders!$G$2:$G$1001,Orders!$N$2:$N$1001,A3) -> 224925 | C3: =SUMIFS(Orders!$I$2:$I$1001,Orders!$N$2:$N$1001,A3) -> 34750.84 | D3: =IF(B3=0,0,C3/B3) -> 0.15449968 | E3: =COUNTIFS(Orders!$N$2:$N$1001,A3) -> 506
A4: Corporate | B4: =SUMIFS(Orders!$G$2:$G$1001,Orders!$N$2:$N$1001,A4) -> 135630 | C4: =SUMIFS(Orders!$I$2:$I$1001,Orders!$N$2:$N$1001,A4) -> 19388.94 | D4: =IF(B4=0,0,C4/B4) -> 0.14295466 | E4: =COUNTIFS(Orders!$N$2:$N$1001,A4) -> 298
A5: Home Office | B5: =SUMIFS(Orders!$G$2:$G$1001,Orders!$N$2:$N$1001,A5) -> 95445 | C5: =SUMIFS(Orders!$I$2:$I$1001,Orders!$N$2:$N$1001,A5) -> 17166.5 | D5: =IF(B5=0,0,C5/B5) -> 0.17985751 | E5: =COUNTIFS(Orders!$N$2:$N$1001,A5) -> 196

Sheet Monthly_Trend
A1: Monthly Sales Trend
A2: Month | B2: Total_Sales
A3: 1 | B3: =SUMIFS(Orders!$G$2:$G$1001,Orders!$J$2:$J$1001,A3) -> 36980
A4: 2 | B4: =SUMIFS(Orders!$G$2:$G$1001,Orders!$J$2:$J$1001,A4) -> 44060
A5: 3 | B5: =SUMIFS(Orders!$G$2:$G$1001,Orders!$J$2:$J$1001,A5) -> 28990
A6: 4 | B6: =SUMIFS(Orders!$G$2:$G$1001,Orders!$J$2:$J$1001,A6) -> 33870
A7: 5 | B7: =SUMIFS(Orders!$G$2:$G$1001,Orders!$J$2:$J$1001,A7) -> 53150
A8: 6 | B8: =SUMIFS(Orders!$G$2:$G$1001,Orders!$J$2:$J$1001,A8) -> 36715
A9: 7 | B9: =SUMIFS(Orders!$G$2:$G$1001,Orders!$J$2:$J$1001,A9) -> 35465
A10: 8 | B10: =SUMIFS(Orders!$G$2:$G$1001,Orders!$J$2:$J$1001,A10) -> 36960
A11: 9 | B11: =SUMIFS(Orders!$G$2:$G$1001,Orders!$J$2:$J$1001,A11) -> 23620
A12: 10 | B12: =SUMIFS(Orders!$G$2:$G$1001,Orders!$J$2:$J$1001,A12) -> 46580
A13: 11 | B13: =SUMIFS(Orders!$G$2:$G$1001,Orders!$J$2:$J$1001,A13) -> 34920
A14: 12 | B14: =SUMIFS(Orders!$G$2:$G$1001,Orders!$J$2:$J$1001,A14) -> 44690

Sheet Top10_Customers
A1: Top 10 Customers by Revenue
A2: Rank | B2: Customer_Name | C2: Region | D2: Segment | E2: Total_Revenue
A3: 1 | B3: Daniel Miller | C3: South | D3: Corporate | E3: 2100
A4: 2 | B4: Emily Miller | C4: South | D4: Corporate | E4: 2000
A5: 3 | B5: Joshua Williams | C5: West | D5: Consumer | E5: 2000
A6: 4 | B6: Patricia Brown | C6: West | D6: Consumer | E6: 2000
A7: 5 | B7: John Gonzalez | C7: South | D7: Consumer | E7: 2000
A8: 6 | B8: Patricia Miller | C8: South | D8: Corporate | E8: 2000
A9: 7 | B9: Paul Moore | C9: North | D9: Home Office | E9: 2000
A10: 8 | B10: Kenneth Lewis | C10: West | D10: Consumer | E10: 2000
A11: 9 | B11: Kevin Allen | C11: East | D11: Home Office | E11: 2000
A12: 10 | B12: Elizabeth Martinez | C12: West | D12: Consumer | E12: 2000
